aichar-1.0.5.dist-info/METADATA
aichar-1.0.5.dist-info/WHEEL
aichar-1.0.5.dist-info/licenses/LICENSE
aichar/__init__.py
aichar/__init__.pyi
aichar/aichar.cp313-win32.pyd
aichar/py.typed
aichar-1.0.5.dist-info/RECORD
