Metadata-Version: 2.4
Name: aichar
Version: 1.0.5
Classifier: Programming Language :: Rust
Classifier: Programming Language :: Python :: Implementation :: CPython
Classifier: Programming Language :: Python :: Implementation :: PyPy
License-File: LICENSE
Summary: Library written in Rust for creating/transporting/parsing AI characters between different frontends (TavernAI, SillyTavern, TextGenerationWebUI, AI-companion, Pygmalion) and generation tools (Character Factory)
Keywords: character cards,Rust,parser,editor,TavernAI,SillyTavern,TextGenerationWebUI,AI-Companion,Pygmalion,Character Factory
Author-email: Hubert Kasperek <hubertkasp13@gmail.com>
Requires-Python: >=3.7
Project-URL: Repository, https://github.com/Hukasx0/aichar
Project-URL: Documentation, https://github.com/Hukasx0/aichar/blob/main/README.md
